hapitools/__init__.py
hapitools/dbmanager/__init__.py
hapitools/dbmanager/mysql/__init__.py
hapitools/dbmanager/mysql/db.py
hapitools/dbmanager/mysql/sqlutils.py
hapitools/logger/__init__.py
hapitools/logger/log.py
hapitools-0.1.0.data/data/requirements.txt
hapitools-0.1.0.dist-info/METADATA
hapitools-0.1.0.dist-info/WHEEL
hapitools-0.1.0.dist-info/top_level.txt
hapitools-0.1.0.dist-info/RECORD
